vdocs/ARP Interfaces/CSV/.gitignore
vdocs/ARP Interfaces/HTML/.gitignore
vdocs/ARP Interfaces/JSON/.gitignore
vdocs/ARP Interfaces/Markdown/.gitignore
vdocs/ARP Interfaces/Mindmap/.gitignore
vdocs/ARP Interfaces/YAML/.gitignore
vdocs/BFD Sessions/CSV/.gitignore
vdocs/BFD Sessions/HTML/.gitignore
vdocs/BFD Sessions/JSON/.gitignore
vdocs/BFD Sessions/Markdown/.gitignore
vdocs/BFD Sessions/Mindmap/.gitignore
vdocs/BFD Sessions/YAML/.gitignore
vdocs/BFD Sessions From Device/CSV/.gitignore
vdocs/BFD Sessions From Device/HTML/.gitignore
vdocs/BFD Sessions From Device/JSON/.gitignore
vdocs/BFD Sessions From Device/Markdown/.gitignore
vdocs/BFD Sessions From Device/Mindmap/.gitignore
vdocs/BFD Sessions From Device/YAML/.gitignore
vdocs/BFD Summary/CSV/.gitignore
vdocs/BFD Summary/HTML/.gitignore
vdocs/BFD Summary/JSON/.gitignore
vdocs/BFD Summary/Markdown/.gitignore
vdocs/BFD Summary/Mindmap/.gitignore
vdocs/BFD Summary/YAML/.gitignore
vdocs/CEdge Interfaces/CSV/.gitignore
vdocs/CEdge Interfaces/HTML/.gitignore
vdocs/CEdge Interfaces/JSON/.gitignore
vdocs/CEdge Interfaces/Markdown/.gitignore
vdocs/CEdge Interfaces/Mindmap/.gitignore
vdocs/CEdge Interfaces/YAML/.gitignore
vdocs/Control Connection/CSV/.gitignore
vdocs/Control Connection/HTML/.gitignore
vdocs/Control Connection/JSON/.gitignore
vdocs/Control Connection/Markdown/.gitignore
vdocs/Control Connection/Mindmap/.gitignore
vdocs/Control Connection/YAML/.gitignore
vdocs/Control Local Property/CSV/.gitignore
vdocs/Control Local Property/HTML/.gitignore
vdocs/Control Local Property/JSON/.gitignore
vdocs/Control Local Property/Markdown/.gitignore
vdocs/Control Local Property/Mindmap/.gitignore
vdocs/Control Local Property/YAML/.gitignore
vdocs/Control WAN Interfaces/CSV/.gitignore
vdocs/Control WAN Interfaces/HTML/.gitignore
vdocs/Control WAN Interfaces/JSON/.gitignore
vdocs/Control WAN Interfaces/Markdown/.gitignore
vdocs/Control WAN Interfaces/Mindmap/.gitignore
vdocs/Control WAN Interfaces/YAML/.gitignore
vdocs-0.1.8.dist-info/METADATA
vdocs-0.1.8.dist-info/WHEEL
vdocs-0.1.8.dist-info/LICENSE
vdocs-0.1.8.dist-info/entry_points.txt
vdocs-0.1.8.dist-info/RECORD
